osmscigrid/CSV.py
osmscigrid/C_colors.py
osmscigrid/K_Component.py
osmscigrid/K_Netze.py
osmscigrid/M_CSV.py
osmscigrid/M_DataAnalysis.py
osmscigrid/M_GetCountry.py
osmscigrid/M_OSM.py
osmscigrid/M_OSM_PipeSegmenting.py
osmscigrid/M_OSM_convert.py
osmscigrid/M_PCKL.py
osmscigrid/M_PlotObjects.py
osmscigrid/OSM_Pipeline_CountryCode.py
osmscigrid/OSMpath.py
osmscigrid/PosFind.py
osmscigrid/Processing.py
osmscigrid/_init_.py
osmscigrid/geojson_export.py
osmscigrid/osm_tags.py
osmscigrid/path_segmenter.py
osmscigrid-1.1.0.dist-info/LICENSE
osmscigrid-1.1.0.dist-info/METADATA
osmscigrid-1.1.0.dist-info/WHEEL
osmscigrid-1.1.0.dist-info/top_level.txt
osmscigrid-1.1.0.dist-info/RECORD
